monobank/__init__.py
monobank/client.py
monobank/errors.py
monobank/signature.py
monobank/transport.py
monobank/utils.py
monobank-0.4.4.dist-info/WHEEL
monobank-0.4.4.dist-info/METADATA
monobank-0.4.4.dist-info/RECORD
