Metadata-Version: 2.1
Name: monobank
Version: 0.4.4
Summary: Monobank.ua API implementation
Home-page: https://github.com/vitalik/python-monobank
Author: Vitaliy Kucheryaviy
Author-email: ppr.vitaly@gmail.com
Requires-Python: >=3.6,<4.0
Classifier: Programming Language :: Python :: 3
Classifier: Programming Language :: Python :: 3.6
Classifier: Programming Language :: Python :: 3.7
Requires-Dist: ecdsa (>=0.13.2,<0.14.0)
Requires-Dist: requests (>=2.22,<3.0)
